[
 {
  "status": "complete",
  "type": "waiver",
  "metadata": {
   "notes": "Your waiver claim was processed successfully!"
  },
  "created": 1701192901998,
  "settings": {
   "seq": 1,
   "waiver_bid": 0
  },
  "leg": 12,
  "draft_picks": [],
  "creator": "861798755085692928",
  "transaction_id": "1035281703410970624",
  "adds": {
   "5334": 9
  },
  "consenter_ids": [
   9
  ],
  "drops": null,
  "roster_ids": [
   9
  ],
  "status_updated": 1701245290804,
  "waiver_budget": []
 },
 {
  "status": "complete",
  "type": "free_agent",
  "metadata": null,
  "created": 1701192748435,
  "settings": null,
  "leg": 12,
  "draft_picks": [],
  "creator": "861798755085692928",
  "transaction_id": "1035281059321044992",
  "adds": null,
  "consenter_ids": [
   9
  ],
  "drops": {
   "5916": 9
  },
  "roster_ids": [
   9
  ],
  "status_updated": 1701192748435,
  "waiver_budget": []
 },
 {
  "status": "complete",
  "type": "waiver",
  "metadata": {
   "notes": "Your waiver claim was processed successfully!"
  },
  "created": 1701187885169,
  "settings": {
   "seq": 0,
   "waiver_bid": 3
  },
  "leg": 12,
  "draft_picks": [],
  "creator": "862559746694205440",
  "transaction_id": "1035260661305110528",
  "adds": {
   "6945": 3
  },
  "consenter_ids": [
   3
  ],
  "drops": {
   "7044": 3
  },
  "roster_ids": [
   3
  ],
  "status_updated": 1701245290804,
  "waiver_budget": []
 },
 {
  "status": "complete",
  "type": "free_agent",
  "metadata": null,
  "created": 1701020916375,
  "settings": null,
  "leg": 12,
  "draft_picks": [],
  "creator": "740751073198948352",
  "transaction_id": "1034560343424598016",
  "adds": null,
  "consenter_ids": [
   12
  ],
  "drops": {
   "8676": 12
  },
  "roster_ids": [
   12
  ],
  "status_updated": 1701020916375,
  "waiver_budget": []
 },
 {
  "status": "complete",
  "type": "free_agent",
  "metadata": null,
  "created": 1700980057867,
  "settings": null,
  "leg": 12,
  "draft_picks": [],
  "creator": "862499213718704128",
  "transaction_id": "1034388970420912128",
  "adds": {
   "5580": 11
  },
  "consenter_ids": [
   11
  ],
  "drops": {
   "6485": 11
  },
  "roster_ids": [
   11
  ],
  "status_updated": 1700980057867,
  "waiver_budget": []
 },
 {
  "status": "complete",
  "type": "free_agent",
  "metadata": null,
  "created": 1700926890086,
  "settings": null,
  "leg": 12,
  "draft_picks": [],
  "creator": "862499213718704128",
  "transaction_id": "1034165968584392704",
  "adds": {
   "3172": 11
  },
  "consenter_ids": [
   11
  ],
  "drops": {
   "1234": 11
  },
  "roster_ids": [
   11
  ],
  "status_updated": 1700926890086,
  "waiver_budget": []
 },
 {
  "status": "complete",
  "type": "free_agent",
  "metadata": null,
  "created": 1700759375068,
  "settings": null,
  "leg": 12,
  "draft_picks": [],
  "creator": "740751073198948352",
  "transaction_id": "1033463359674482688",
  "adds": {
   "6217": 12
  },
  "consenter_ids": [
   12
  ],
  "drops": {
   "5580": 12
  },
  "roster_ids": [
   12
  ],
  "status_updated": 1700759375068,
  "waiver_budget": []
 },
 {
  "status": "complete",
  "type": "free_agent",
  "metadata": null,
  "created": 1700759291808,
  "settings": null,
  "leg": 12,
  "draft_picks": [],
  "creator": "740751073198948352",
  "transaction_id": "1033463010456731648",
  "adds": {
   "7672": 12
  },
  "consenter_ids": [
   12
  ],
  "drops": {
   "7113": 12
  },
  "roster_ids": [
   12
  ],
  "status_updated": 1700759291808,
  "waiver_budget": []
 },
 {
  "status": "complete",
  "type": "free_agent",
  "metadata": null,
  "created": 1700759173188,
  "settings": null,
  "leg": 12,
  "draft_picks": [],
  "creator": "740751073198948352",
  "transaction_id": "1033462512928391168",
  "adds": {
   "8676": 12
  },
  "consenter_ids": [
   12
  ],
  "drops": {
   "8119": 12
  },
  "roster_ids": [
   12
  ],
  "status_updated": 1700759173188,
  "waiver_budget": []
 },
 {
  "status": "complete",
  "type": "free_agent",
  "metadata": null,
  "created": 1700753843493,
  "settings": null,
  "leg": 12,
  "draft_picks": [],
  "creator": "595464158774878208",
  "transaction_id": "1033440158567333888",
  "adds": {
   "4180": 7
  },
  "consenter_ids": [
   7
  ],
  "drops": null,
  "roster_ids": [
   7
  ],
  "status_updated": 1700753843493,
  "waiver_budget": []
 },
 {
  "status": "complete",
  "type": "free_agent",
  "metadata": null,
  "created": 1700751387348,
  "settings": null,
  "leg": 12,
  "draft_picks": [],
  "creator": "862499213718704128",
  "transaction_id": "1033429856748388352",
  "adds": {
   "6804": 11
  },
  "consenter_ids": [
   11
  ],
  "drops": null,
  "roster_ids": [
   11
  ],
  "status_updated": 1700751387348,
  "waiver_budget": []
 },
 {
  "status": "complete",
  "type": "free_agent",
  "metadata": null,
  "created": 1700665137434,
  "settings": null,
  "leg": 12,
  "draft_picks": [],
  "creator": "740751073198948352",
  "transaction_id": "1033068098389106688",
  "adds": {
   "7113": 12
  },
  "consenter_ids": [
   12
  ],
  "drops": null,
  "roster_ids": [
   12
  ],
  "status_updated": 1700665137434,
  "waiver_budget": []
 },
 {
  "status": "complete",
  "type": "free_agent",
  "metadata": null,
  "created": 1700664969920,
  "settings": null,
  "leg": 12,
  "draft_picks": [],
  "creator": "740751073198948352",
  "transaction_id": "1033067395784466432",
  "adds": null,
  "consenter_ids": [
   12
  ],
  "drops": {
   "7601": 12
  },
  "roster_ids": [
   12
  ],
  "status_updated": 1700664969920,
  "waiver_budget": []
 }
]